sif2jax/__init__.py
sif2jax/_compat.py
sif2jax/_misc.py
sif2jax/_problem.py
sif2jax/py.typed
sif2jax/cutest/__init__.py
sif2jax/cutest/_compat.py
sif2jax/cutest/_bounded_minimisation/README.md
sif2jax/cutest/_bounded_minimisation/__init__.py
sif2jax/cutest/_bounded_minimisation/aircrftb.py
sif2jax/cutest/_bounded_minimisation/bdexp.py
sif2jax/cutest/_bounded_minimisation/biggs3.py
sif2jax/cutest/_bounded_minimisation/biggs5.py
sif2jax/cutest/_bounded_minimisation/box2.py
sif2jax/cutest/_bounded_minimisation/branin.py
sif2jax/cutest/_bounded_minimisation/camel6.py
sif2jax/cutest/_bounded_minimisation/chardis0.py
sif2jax/cutest/_bounded_minimisation/chardis02.py
sif2jax/cutest/_bounded_minimisation/clplatea.py
sif2jax/cutest/_bounded_minimisation/clplateb.py
sif2jax/cutest/_bounded_minimisation/clplatec.py
sif2jax/cutest/_bounded_minimisation/cyclooctls.py
sif2jax/cutest/_bounded_minimisation/degdiag.py
sif2jax/cutest/_bounded_minimisation/degtrid.py
sif2jax/cutest/_bounded_minimisation/degtrid2.py
sif2jax/cutest/_bounded_minimisation/devgla1b.py
sif2jax/cutest/_bounded_minimisation/devgla2b.py
sif2jax/cutest/_bounded_minimisation/dgospec.py
sif2jax/cutest/_bounded_minimisation/diagiqb.py
sif2jax/cutest/_bounded_minimisation/diagiqe.py
sif2jax/cutest/_bounded_minimisation/diagiqt.py
sif2jax/cutest/_bounded_minimisation/diagnqb.py
sif2jax/cutest/_bounded_minimisation/diagnqe.py
sif2jax/cutest/_bounded_minimisation/diagnqt.py
sif2jax/cutest/_bounded_minimisation/diagpqb.py
sif2jax/cutest/_bounded_minimisation/diagpqe.py
sif2jax/cutest/_bounded_minimisation/diagpqt.py
sif2jax/cutest/_bounded_minimisation/eg1.py
sif2jax/cutest/_bounded_minimisation/eggcrateb.py
sif2jax/cutest/_bounded_minimisation/elatvidub.py
sif2jax/cutest/_bounded_minimisation/exp2b.py
sif2jax/cutest/_bounded_minimisation/explin.py
sif2jax/cutest/_bounded_minimisation/explin2.py
sif2jax/cutest/_bounded_minimisation/expquad.py
sif2jax/cutest/_bounded_minimisation/fbrain2ls.py
sif2jax-0.0.8.dist-info/METADATA
sif2jax-0.0.8.dist-info/WHEEL
sif2jax-0.0.8.dist-info/licenses/LICENSE
sif2jax-0.0.8.dist-info/RECORD
