Metadata-Version: 2.4
Name: sif2jax
Version: 0.0.8
Summary: Functionally pure definitions of optimisation problems extracted from Standard Input Format (SIF).
Project-URL: repository, https://github.com/johannahaffner/sif2jax
Author-email: Johanna Haffner <johanna.haffner@bsse.ethz.ch>, John Viljoen <john_viljoen@berkeley.edu>
License:                                  Apache License
License-File: LICENSE
Keywords: jax
Classifier: Development Status :: 3 - Alpha
Classifier: Intended Audience :: Developers
Classifier: Intended Audience :: Science/Research
Classifier: License :: OSI Approved :: Apache Software License
Classifier: Natural Language :: English
Classifier: Programming Language :: Python :: 3
Classifier: Topic :: Scientific/Engineering :: Mathematics
Requires-Python: >=3.10
Requires-Dist: beartype
Requires-Dist: equinox
Requires-Dist: jax>=0.7.2
Requires-Dist: jaxtyping>=0.2.20
Requires-Dist: pytest
Requires-Dist: pytest-benchmark
Requires-Dist: typing-extensions>=4.5.0
Requires-Dist: wadler-lindig>=0.1.0
Provides-Extra: docs
Requires-Dist: griffe==1.7.3; extra == 'docs'
Requires-Dist: hippogriffe==0.2.0; extra == 'docs'
Requires-Dist: mkdocs-include-exclude-files==0.1.0; extra == 'docs'
Requires-Dist: mkdocs-ipynb==0.1.0; extra == 'docs'
Requires-Dist: mkdocs-material==9.6.7; extra == 'docs'
Requires-Dist: mkdocs==1.6.1; extra == 'docs'
Requires-Dist: mkdocstrings[python]==0.28.3; extra == 'docs'
Requires-Dist: pymdown-extensions==10.14.3; extra == 'docs'
